wordpress_poster/client.py
wordpress_poster/exceptions.py
wordpress_poster/utils.py
wordpress_poster-0.1.1.dist-info/METADATA
wordpress_poster-0.1.1.dist-info/WHEEL
wordpress_poster-0.1.1.dist-info/top_level.txt
wordpress_poster-0.1.1.dist-info/RECORD
