Metadata-Version: 2.4
Name: wordpress_poster
Version: 0.1.1
Summary: A Python library for posting content, uploading media, and interacting with the WordPress REST API.
Author-email: Ihor Tykhonenko <tykhonenkoigor@email.com>
Requires-Python: >=3.8
Requires-Dist: requests
Requires-Dist: python-dotenv
Requires-Dist: httpx
